odoo8_addon_l10n_es_toponyms-8.0.2.0.1.99.dev17-py3.6-nspkg.pth
odoo_addons/l10n_es_toponyms/README.rst
odoo_addons/l10n_es_toponyms/__init__.py
odoo_addons/l10n_es_toponyms/__openerp__.py
odoo_addons/l10n_es_toponyms/gen_src/README.md
odoo_addons/l10n_es_toponyms/gen_src/gen_toponyms_geonames.py
odoo_addons/l10n_es_toponyms/i18n/bg.po
odoo_addons/l10n_es_toponyms/i18n/ca.po
odoo_addons/l10n_es_toponyms/i18n/ca_ES.po
odoo_addons/l10n_es_toponyms/i18n/cs.po
odoo_addons/l10n_es_toponyms/i18n/en_US.po
odoo_addons/l10n_es_toponyms/i18n/es.po
odoo_addons/l10n_es_toponyms/i18n/es_CO.po
odoo_addons/l10n_es_toponyms/i18n/es_CR.po
odoo_addons/l10n_es_toponyms/i18n/eu.po
odoo_addons/l10n_es_toponyms/i18n/fr.po
odoo_addons/l10n_es_toponyms/i18n/gl.po
odoo_addons/l10n_es_toponyms/i18n/hr.po
odoo_addons/l10n_es_toponyms/i18n/l10n_es_toponyms.pot
odoo_addons/l10n_es_toponyms/i18n/nl.po
odoo_addons/l10n_es_toponyms/i18n/pl.po
odoo_addons/l10n_es_toponyms/i18n/pt.po
odoo_addons/l10n_es_toponyms/i18n/pt_BR.po
odoo_addons/l10n_es_toponyms/i18n/ru.po
odoo_addons/l10n_es_toponyms/i18n/sl.po
odoo_addons/l10n_es_toponyms/i18n/sv.po
odoo_addons/l10n_es_toponyms/i18n/tr.po
odoo_addons/l10n_es_toponyms/i18n/vi.po
odoo_addons/l10n_es_toponyms/images/l10n_es_toponyms_config.png
odoo_addons/l10n_es_toponyms/static/description/icon.png
odoo_addons/l10n_es_toponyms/static/src/img/icon.svg
odoo_addons/l10n_es_toponyms/tests/__init__.py
odoo_addons/l10n_es_toponyms/tests/test_l10n_es_toponyms.py
odoo_addons/l10n_es_toponyms/wizard/__init__.py
odoo_addons/l10n_es_toponyms/wizard/geonames_import.py
odoo_addons/l10n_es_toponyms/wizard/l10n_es_toponyms_states_both.xml
odoo_addons/l10n_es_toponyms/wizard/l10n_es_toponyms_states_official.xml
odoo_addons/l10n_es_toponyms/wizard/l10n_es_toponyms_states_spanish.xml
odoo_addons/l10n_es_toponyms/wizard/l10n_es_toponyms_wizard.py
odoo_addons/l10n_es_toponyms/wizard/l10n_es_toponyms_wizard.xml
odoo_addons/l10n_es_toponyms/wizard/l10n_es_toponyms_zipcodes.xml
odoo8_addon_l10n_es_toponyms-8.0.2.0.1.99.dev17.dist-info/METADATA
odoo8_addon_l10n_es_toponyms-8.0.2.0.1.99.dev17.dist-info/WHEEL
odoo8_addon_l10n_es_toponyms-8.0.2.0.1.99.dev17.dist-info/namespace_packages.txt
odoo8_addon_l10n_es_toponyms-8.0.2.0.1.99.dev17.dist-info/top_level.txt
odoo8_addon_l10n_es_toponyms-8.0.2.0.1.99.dev17.dist-info/RECORD
